getbib
