Metadata-Version: 1.0
Name: getbib
Version: 1.0.6
Summary: Pulls an author's bibliography from Westlaw.
Home-page: UNKNOWN
Author: Samuel Alexander
Author-email: salexander2000@gmail.com
License: GPL
Platform: UNKNOWN
